misk/__init__.py
misk/functions.py
misk/timers.py
misk-0.8.1.dist-info/LICENSE.txt
misk-0.8.1.dist-info/METADATA
misk-0.8.1.dist-info/WHEEL
misk-0.8.1.dist-info/top_level.txt
misk-0.8.1.dist-info/RECORD
