Metadata-Version: 2.1
Name: misk
Version: 0.8.1
Summary: Miscellaneous useful bits for python 3.
Home-page: https://github.com/marzer/misk
Download-URL: https://pypi.org/project/misk/
Author: Mark Gillard
Author-email: mark.gillard@outlook.com.au
License: MIT
Project-URL: Source, https://github.com/marzer/misk
Project-URL: Tracker, https://github.com/marzer/misk/issues
Keywords: utilities
Requires-Python: >=3.7
License-File: LICENSE.txt
Requires-Dist: requests
